channels_prometheus/__init__.py
channels_prometheus/apps.py
channels_prometheus/decorators.py
channels_prometheus/helpers.py
channels_prometheus/urls.py
channels_prometheus/views.py
django_channels_prometheus-1.0.0.dist-info/LICENSE
django_channels_prometheus-1.0.0.dist-info/METADATA
django_channels_prometheus-1.0.0.dist-info/WHEEL
django_channels_prometheus-1.0.0.dist-info/RECORD
