Metadata-Version: 2.1
Name: django-channels-prometheus
Version: 1.0.0
Summary: Very simple package that enables a Prometheus endpoint, to check how many websocket connections are currently open.
Home-page: https://github.com/Frodothedwarf/django-channels-prometheus
License: MIT
Keywords: prometheus,channels,webhook,webhooks,django
Author: Frederich Pedersen
Author-email: frodo@hobbits.dk
Requires-Python: >=3.8,<4.0
Classifier: Development Status :: 3 - Alpha
Classifier: Framework :: Django
Classifier: Framework :: Django :: 4.0
Classifier: Framework :: Django :: 4.1
Classifier: Framework :: Django :: 4.2
Classifier: Framework :: Django :: 5.0
Classifier: Intended Audience :: Developers
Classifier: License :: OSI Approved :: MIT License
Classifier: Natural Language :: English
Classifier: Programming Language :: Python :: 3
Classifier: Programming Language :: Python :: 3.8
Classifier: Programming Language :: Python :: 3.9
Classifier: Programming Language :: Python :: 3.10
Classifier: Programming Language :: Python :: 3.11
Classifier: Programming Language :: Python :: 3.12
Provides-Extra: test
Requires-Dist: channels
Project-URL: Repository, https://github.com/Frodothedwarf/django-channels-prometheus
